pytest_api/__init__.py
pytest_api/asgi.py
pytest_api/responders.py
pytest_api/schemas.py
pytest_api/types.py
pytest_api-0.1.4.dist-info/WHEEL
pytest_api-0.1.4.dist-info/METADATA
pytest_api-0.1.4.dist-info/RECORD
